[
    { "id": "conf", "nome": "Daniel de Andrade Varela" },
    { "id": "conf", "nome": "Rodrigo Nogueira" },
    { "id": "conf", "nome": "Alexandre Aguiar Amaral" },
    { "id": "conf", "nome": "Daniel Anderli" },
    { "id": "conf", "nome": "Marcelo Fernando Rauber" },

    { "id": "conf", "nome": "Lucas Cerdeira" },
    { "id": "conf", "nome": "Leonardo Croda" },
    { "id": "conf", "nome": "Victor Augusto Rosa" },
    { "id": "conf", "nome": "Jhonata Simonetto" },
    { "id": "conf", "nome": "Eli Neto" },
    { "id": "conf", "nome": "Nicolas Oliveira" },
    { "id": "conf", "nome": "Marissol Bernardes" },
    { "id": "conf", "nome": "Helena Tamanini" },
    { "id": "conf", "nome": "" },
    { "id": "conf", "nome": "" },
    { "id": "conf", "nome": "" },
    { "id": "conf", "nome": "" },
    { "id": "conf", "nome": "" },
    { "id": "conf", "nome": "" },
    { "id": "conf", "nome": "" },
    { "id": "conf", "nome": "" },
    { "id": "conf", "nome": "" },
    { "id": "conf", "nome": "" },
    { "id": "conf", "nome": "" },
    { "id": "conf", "nome": "" }
]